{"name":"Ouracm","tagline":"优雅简洁的ACM-ICPC队伍风采展示系统，基于Bootstrap和ThinkPHP！","body":"OurAcm  \r\n======  \r\n  \r\n优雅简洁的ACM-ICPC队伍风采展示系统，基于Bootstrap和ThinkPHP！  \r\n  \r\n*简洁优雅的界面  \r\n*支持WF、Regional等类型的ACM-ICPC比赛展示  \r\n*酷炫版与表单版两种展示模式  \r\n*支持教练团队展示  \r\n*简易强大的报名系统，支持内部活动、注册字段自定义、审核、注册信息指导出等功能  \r\n*“码池”功能，保存代码，分享代码  \r\n*支持“我们”展示模块  \r\n*支持OnlineJudge展示  \r\n*操作简易、功能强大的后台管理功能  \r\n*用户系统OnlineJudge关联模式  \r\n*支持邀请码机制，快速添加新队员  \r\n  \r\n  \r\n系统要求  \r\n========  \r\n  \r\n建议使用PHP 5.3+环境，MySQL 5.1+数据库，  \r\n浏览器支持Chrome、Firefox、IE10+等，IE低版本显示不友好，会有提示信息。  \r\n  \r\n  \r\n部署说明  \r\n========  \r\n  \r\n1、使用phpmyadmin或其它工具，导入/db目录下对应版本的数据库文件；  \r\n2、将www文件夹下所有文件拷贝到服务器的HTTP服务目录下；  \r\n3、修改服务器上/Goldbirds/Home/Common/function.php中的4个OnlineJudge接口；  \r\n4、修改服务器上/Goldbirds/Home/Conf/config.php中的数据库配置选项；  \r\n5、请确保服务器上/upload、/Goldbirds/Runtime（该文件夹首次访问时会创建）这2个目录具有写权限；  \r\n6、访问index.php尝试能否正常访问；  \r\n7、登录OnlineJudge，并访问index.php?z=setting，以邀请码\"iloveacmiloveacm\"关联带管理权的OnlineJudge账户；  \r\n8、关联后，点击\"个人中心\"，可在里面进行相应配置管理。  \r\n","google":"","note":"Don't delete this file! It's used internally to help with page regeneration."}